snova/__init__.py
snova/src/access_tokens.txt
snova/src/body.json
snova/src/headers.json
snova/src/mask_lmc.json
snova/src/user_agents.txt
snova-0.1.3.dist-info/LICENSE
snova-0.1.3.dist-info/METADATA
snova-0.1.3.dist-info/WHEEL
snova-0.1.3.dist-info/RECORD
